tryangle/__init__.py
tryangle/core/__init__.py
tryangle/core/base.py
tryangle/core/methods.py
tryangle/ensemble/__init__.py
tryangle/ensemble/base.py
tryangle/ensemble/losses.py
tryangle/ensemble/optimizers.py
tryangle/metrics/__init__.py
tryangle/metrics/base.py
tryangle/metrics/score.py
tryangle/model_selection/__init__.py
tryangle/model_selection/split.py
tryangle/utils/__init__.py
tryangle/utils/datasets.py
tryangle/utils/data/cas_test.csv
tryangle/utils/data/cas_train.csv
tryangle/utils/data/sme_test.csv
tryangle/utils/data/sme_train.csv
tryangle/utils/data/swiss_test.csv
tryangle/utils/data/swiss_train.csv
tryangle-0.2.2.dist-info/LICENSE
tryangle-0.2.2.dist-info/METADATA
tryangle-0.2.2.dist-info/WHEEL
tryangle-0.2.2.dist-info/top_level.txt
tryangle-0.2.2.dist-info/RECORD
