Metadata-Version: 2.1
Name: tryangle
Version: 0.2.2
Summary: Tryangle Package - Scientific P&C Loss Reserving
Maintainer-email: Caesar Balona <caesar.balona@gmail.com>
License: MPL-2.0
Project-URL: Homepage, https://github.com/casact/tryangle
Classifier: Intended Audience :: Financial and Insurance Industry
Classifier: Intended Audience :: Science/Research
Classifier: License :: OSI Approved :: Mozilla Public License 2.0 (MPL 2.0)
Classifier: Operating System :: OS Independent
Classifier: Programming Language :: Python :: 3
Classifier: Topic :: Office/Business :: Financial
Classifier: Topic :: Scientific/Engineering :: Artificial Intelligence
Requires-Python: >=3.11
License-File: LICENSE
Requires-Dist: chainladder (<=0.8.14)
Requires-Dist: pandas (<2.0)
Requires-Dist: scikit-learn (>=1.2)
Provides-Extra: dev
Requires-Dist: ruff ; extra == 'dev'
Requires-Dist: black ; extra == 'dev'
Requires-Dist: mypy ; extra == 'dev'
Requires-Dist: pytest ; extra == 'dev'
Requires-Dist: tox ; extra == 'dev'
Requires-Dist: twine ; extra == 'dev'
